canvas_langchain/__init__.py
canvas_langchain/base.py
canvas_langchain/canvas.py
canvas_langchain/client.py
canvas_langchain/client_getters.py
canvas_langchain/sections/__init__.py
canvas_langchain/sections/announcements.py
canvas_langchain/sections/assignments.py
canvas_langchain/sections/files.py
canvas_langchain/sections/modules.py
canvas_langchain/sections/pages.py
canvas_langchain/sections/syllabus.py
canvas_langchain/utils/__init__.py
canvas_langchain/utils/logging.py
canvas_langchain-0.9.20.dist-info/licenses/LICENSE.txt
canvas_langchain-0.9.20.dist-info/METADATA
canvas_langchain-0.9.20.dist-info/WHEEL
canvas_langchain-0.9.20.dist-info/top_level.txt
canvas_langchain-0.9.20.dist-info/RECORD
