Metadata-Version: 2.4
Name: canvas_langchain
Version: 0.9.20
Summary: A canvas langchain integration
Home-page: https://github.com/umich-its-ai/langchain-doc-canvas
Author: University of Michigan
Author-email: noreply@umich.edu
Classifier: Development Status :: 3 - Alpha
Classifier: License :: OSI Approved :: GNU General Public License (GPL)
Requires-Python: >=3.10
License-File: LICENSE.txt
Requires-Dist: langchain
Requires-Dist: langchain-community
Requires-Dist: unstructured[docx,pptx]
Requires-Dist: canvasapi
Requires-Dist: beautifulsoup4
Requires-Dist: lxml
Requires-Dist: PyPDF2[crypto]
Requires-Dist: docx2txt
Requires-Dist: striprtf
Requires-Dist: pandas
Requires-Dist: pydantic
Requires-Dist: openpyxl
Requires-Dist: xlrd
Requires-Dist: markdown
Requires-Dist: pytz
Dynamic: author
Dynamic: author-email
Dynamic: classifier
Dynamic: description
Dynamic: description-content-type
Dynamic: home-page
Dynamic: license-file
Dynamic: requires-dist
Dynamic: requires-python
Dynamic: summary
